<?xml version="1.0" encoding="UTF-8" standalone="no"?>
<!-- pycsw 1.10.5 -->
<csw:GetRecordsResponse xmlns:apiso="http://www.opengis.net/cat/csw/apiso/1.0" xmlns:atom="http://www.w3.org/2005/Atom" xmlns:csw="http://www.opengis.net/cat/csw/2.0.2" xmlns:dc="http://purl.org/dc/elements/1.1/" xmlns:dct="http://purl.org/dc/terms/" xmlns:dif="http://gcmd.gsfc.nasa.gov/Aboutus/xml/dif/" xmlns:fgdc="http://www.opengis.net/cat/csw/csdgm" xmlns:gco="http://www.isotc211.org/2005/gco" xmlns:gmd="http://www.isotc211.org/2005/gmd" xmlns:gml="http://www.opengis.net/gml" xmlns:inspire_common="http://inspire.ec.europa.eu/schemas/common/1.0" xmlns:inspire_ds="http://inspire.ec.europa.eu/schemas/inspire_ds/1.0" xmlns:ogc="http://www.opengis.net/ogc" xmlns:os="http://a9.com/-/spec/opensearch/1.1/" xmlns:ows="http://www.opengis.net/ows" xmlns:rdf="http://www.w3.org/1999/02/22-rdf-syntax-ns#" xmlns:sitemap="http://www.sitemaps.org/schemas/sitemap/0.9" xmlns:soapenv="http://www.w3.org/2003/05/soap-envelope" xmlns:srv="http://www.isotc211.org/2005/srv" xmlns:xlink="http://www.w3.org/1999/xlink" xmlns:xs="http://www.w3.org/2001/XMLSchema" xmlns:xsi="http://www.w3.org/2001/XMLSchema-instance" version="2.0.2" xsi:schemaLocation="http://www.opengis.net/cat/csw/2.0.2 http://schemas.opengis.net/csw/2.0.2/CSW-discovery.xsd"><csw:SearchStatus timestamp="2020-07-20T17:40:14Z"/><csw:SearchResults nextRecord="0" numberOfRecordsMatched="1" numberOfRecordsReturned="1" recordSchema="http://www.opengis.net/cat/csw/2.0.2" elementSet="full"><csw:Record><dc:identifier>gov.noaa.nmfs.inport:39284</dc:identifier><dc:title>Xantus's murrelet at-sea density off California</dc:title><dc:type>dataset</dc:type><dc:subject>Environmental Monitoring</dc:subject><dc:subject>EARTH SCIENCE &gt; Oceans &gt; Marine Biology &gt; Marine Birds</dc:subject><dc:subject>DOC/NOAA/NOS/NCCOS &gt; National Centers for Coastal Ocean Science</dc:subject><dc:subject>National Ocean Service</dc:subject><dc:subject>NOAA</dc:subject><dc:subject>U.S. Department of Commerce</dc:subject><dc:subject>Earth Science &gt; Biological Classification &gt; Animals/Vertebrates &gt; Birds &gt; Waders/Gulls/Auks And Allies</dc:subject><dc:subject>Earth Science &gt; Biosphere &gt; Ecological Dynamics &gt; Community Dynamics &gt; Community Structure</dc:subject><dc:subject>Earth Science &gt; Biosphere &gt; Ecological Dynamics &gt; Ecosystem Functions</dc:subject><dc:subject>Earth Science &gt; Biosphere &gt; Ecological Dynamics &gt; Species/Population Interactions &gt; Use/Feeding Habitats</dc:subject><dc:subject>Earth Science &gt; Biosphere &gt; Ecosystems &gt; Marine Ecosystems &gt; Benthic</dc:subject><dc:subject>Earth Science &gt; Biosphere &gt; Ecosystems &gt; Marine Ecosystems &gt; Pelagic</dc:subject><dc:subject>Earth Science &gt; Human Dimensions &gt; Environmental Governance/Management &gt; Environmental Assessments</dc:subject><dc:subject>Earth Science Services &gt; Models &gt; Dynamic Vegetation/Ecosystem Models</dc:subject><dc:subject>California</dc:subject><dc:subject>Channel Islands</dc:subject><dc:subject>Continent &gt; North America &gt; United States Of America &gt; California</dc:subject><dc:subject>Aerial surveys</dc:subject><dc:subject>DOC/NOAA/NOS/NCCOS &gt; National Centers for Coastal Ocean Science</dc:subject><dc:subject> National Ocean Service</dc:subject><dc:subject> NOAA</dc:subject><dc:subject> U.S. Department of Commerce</dc:subject><dc:subject>CINMS_Assessment</dc:subject><dc:subject scheme="http://www.isotc211.org/2005/resources/Codelist/gmxCodelists.xml#MD_TopicCategoryCode">environment</dc:subject><dct:references scheme="WWW:LINK-1.0-http--link">http://coastalscience.noaa.gov/datasets/ccma/biogeo/cinms/Chap_5_Data/cdas_xantu.ZIP</dct:references><dct:modified>2019-06-04T13:14:25</dct:modified><dct:abstract>The National Marine Sanctuary Program (NMSP) updates and revises the management plans for each of its 13 sanctuaries. This process, which is open to the public, enables each site to revisit the reasons for sanctuary designation and assess whether they are meeting their goals, as well as to set new goals consistent with the mandates of the National Marine Sanctuaries Act. Issues raised by the public during this process are evaluated and a determination is made as to whether they will be incorporated into the updated plan. Many of these issues focus on topics such as the implementation of marine zoning or sanctuary boundary adjustments, both of which require information on the distribution of resources within and around the sanctuary. Recognizing this, NMSP and NOAAs National Centers for Coastal Ocean Science (NCCOS) formalized an agreement to collaborate in the revision process by developing such information through a series of biogeographic assessments conducted in selected sanctuaries. The resulting products are then supplied to sanctuary managers and staff for use in the policy and decision making process. This collaborative effort began along the west coast of the U.S. with the Cordell Bank, Gulf of Farallones, and Monterey Bay national marine sanctuaries, and is herein centered on the Channel Islands National Marine Sanctuary (CINMS).</dct:abstract><dc:date>2019-06-04T13:14:25</dc:date><dc:rights>otherRestrictions</dc:rights><ows:BoundingBox crs="urn:x-ogc:def:crs:EPSG:6.11:4326" dimensions="2"><ows:LowerCorner>31.86 -126.5</ows:LowerCorner><ows:UpperCorner>42.11 -117.11</ows:UpperCorner></ows:BoundingBox></csw:Record></csw:SearchResults></csw:GetRecordsResponse>
